LICENSE
MANIFEST.in
README.md
install_script.sh
setup.py
cpp/CMakeLists.txt
cpp/cmake/FindForexConnectAPI.cmake
cpp/include/ForexConnect.h
cpp/include/IAddRef.h
cpp/include/IError.h
cpp/include/IO2GColumn.h
cpp/include/IO2GCommissionsProvider.h
cpp/include/IO2GLoginRules.h
cpp/include/IO2GPermissionChecker.h
cpp/include/IO2GRequest.h
cpp/include/IO2GResponse.h
cpp/include/IO2GRow.h
cpp/include/IO2GSession.h
cpp/include/IO2GTable.h
cpp/include/IO2GTimeFrame.h
cpp/include/IO2GTradingSettingsProvider.h
cpp/include/O2G2ptr.h
cpp/include/O2GDateUtils.h
cpp/include/O2GEnum.h
cpp/include/O2GOrderType.h
cpp/include/O2GRequestParamsEnum.h
cpp/include/O2GTransport.h
cpp/include/TO2GThreadSafeAddRefImpl.h
cpp/include/interfaces_all.h
cpp/include/Enums/AccountsColumnsEnum.h
cpp/include/Enums/ClosedTradesColumnsEnum.h
cpp/include/Enums/MessagesColumnsEnum.h
cpp/include/Enums/OffersColumnsEnum.h
cpp/include/Enums/OrdersColumnsEnum.h
cpp/include/Enums/SummariesColumnsEnum.h
cpp/include/Enums/TradesColumnsEnum.h
cpp/include/Readers/IO2GLastOrderUpdateResponseReader.h
cpp/include/Readers/IO2GLevel2MarketDataUpdatesReader.h
cpp/include/Readers/IO2GMarketDataResponseReader.h
cpp/include/Readers/IO2GMarketDataSnapshotResponseReader.h
cpp/include/Readers/IO2GOrderResponseReader.h
cpp/include/Readers/IO2GSystemProperties.h
cpp/include/Readers/IO2GTablesUpdatesReader.h
cpp/include/Readers/IO2GTimeConverter.h
cpp/include/Rows/IO2GAccountRow.h
cpp/include/Rows/IO2GClosedTradeRow.h
cpp/include/Rows/IO2GMessageRow.h
cpp/include/Rows/IO2GOfferRow.h
cpp/include/Rows/IO2GOrderRow.h
cpp/include/Rows/IO2GSummaryRow.h
cpp/include/Rows/IO2GTradeRow.h
cpp/lib/libForexConnect.so
cpp/lib/libForexConnect.so.1.4.1
cpp/lib/libfxmsg.so
cpp/lib/libfxmsg.so.1.4.1
cpp/lib/libfxtp.so
cpp/lib/libfxtp.so.1.4.1
cpp/lib/libgsexpat.so
cpp/lib/libgsexpat.so.1.4.1
cpp/lib/libgstool3.so
cpp/lib/libgstool3.so.1.4.1
cpp/lib/libhttplib.so
cpp/lib/libhttplib.so.1.4.1
cpp/lib/liblog4cplus.so
cpp/lib/liblog4cplus.so.1.0
fxcpy.egg-info/PKG-INFO
fxcpy.egg-info/SOURCES.txt
fxcpy.egg-info/dependency_links.txt
fxcpy.egg-info/top_level.txt
