Metadata-Version: 1.1
Name: fxcpy
Version: 1.2.2a7
Summary: https://github.com/JamesKBowler/fxcpy
Home-page: https://github.com/JamesKBowler/fxcpy
Author: James K Bowler
Author-email: james.bowler@datacentauri.com
License: MIT
Project-URL: Say Thanks!, https://www.linkedin.com/in/jamesbowler/
Project-URL: Funding, https://www.cancerresearchuk.org/support-us/donate
Project-URL: Source, https://github.com/JamesKBowler/fxcpy/
Project-URL: Bug Reports, https://github.com/JamesKBowler
Keywords: fxcm api trading
Platform: UNKNOWN
Classifier: Development Status :: 3 - Alpha
Classifier: Intended Audience :: Developers
Classifier: Topic :: Software Development :: Build Tools
Classifier: License :: OSI Approved :: MIT License
Classifier: Programming Language :: Python :: 3.5
Classifier: Programming Language :: Python :: 3.6
